gds_metrics/__init__.py
gds_metrics/gunicorn.py
gds_metrics/metrics.py
gds_metrics/version.py
tests/__init__.py
tests/conftest.py
tests/test_gds_metrics.py
tests/test_metrics.py
gds_metrics-0.2.4.dist-info/LICENSE
gds_metrics-0.2.4.dist-info/METADATA
gds_metrics-0.2.4.dist-info/WHEEL
gds_metrics-0.2.4.dist-info/top_level.txt
gds_metrics-0.2.4.dist-info/RECORD
