Metadata-Version: 2.1
Name: gds-metrics
Version: 0.2.4
Summary: Library for Prometheus instrumentation in Python/Flask based apps
Home-page: https://github.com/alphagov/gds_metrics_python
Author: Government Digital Service
Author-email: UNKNOWN
License: MIT
Keywords: gds reliability engineering metrics
Platform: UNKNOWN
Classifier: Intended Audience :: Developers
Classifier: Intended Audience :: Information Technology
Classifier: Intended Audience :: System Administrators
Classifier: Programming Language :: Python
Classifier: Programming Language :: Python :: 3
Classifier: Topic :: System :: Monitoring
Classifier: License :: OSI Approved :: MIT License
Requires-Dist: prometheus-client (<1.0.0,>=0.2.0)
Requires-Dist: Flask (>=0.10)
Requires-Dist: blinker (>=1.4)
